kubernetes_job/__init__.py
kubernetes_job/__main__.py
kubernetes_job/__version__.py
kubernetes_job/job_func_def.py
kubernetes_job/job_manager.py
kubernetes_job-0.3.3.dist-info/LICENSE
kubernetes_job-0.3.3.dist-info/METADATA
kubernetes_job-0.3.3.dist-info/WHEEL
kubernetes_job-0.3.3.dist-info/entry_points.txt
kubernetes_job-0.3.3.dist-info/top_level.txt
kubernetes_job-0.3.3.dist-info/RECORD
