Metadata-Version: 2.1
Name: kubernetes-job
Version: 0.3.3
Summary: Simple Kubernetes job creation; a Python library for starting a Kubernetes batch job as a normal Python function call.
Home-page: https://gitlab.com/roemer/kubernetes-job
Author: Roemer Claasen
Author-email: roemer.claasen@gmail.com
License: UNKNOWN
Project-URL: Documentation, https://kubernetes-job.readthedocs.io
Platform: UNKNOWN
Classifier: Programming Language :: Python :: 3
Classifier: License :: OSI Approved :: MIT License
Classifier: Operating System :: OS Independent
Requires-Python: >=3.6
Requires-Dist: kubernetes (>=12.0.1)
